equities/__init__.py
equities/api.py
equities/models.py
equities/static.py
equities-4.2.12.dist-info/LICENSE
equities-4.2.12.dist-info/METADATA
equities-4.2.12.dist-info/WHEEL
equities-4.2.12.dist-info/top_level.txt
equities-4.2.12.dist-info/RECORD
