Metadata-Version: 2.1
Name: equities
Version: 4.2.12
Summary: equities aims to democratize access to public company data.
Home-page: https://github.com/ljc-codes/equities.git
Author: Tiger_Shark
Author-email: ljwcharles@gmail.com
License: UNKNOWN
Keywords: sec stock stockmarket equities equity data financials financial company public companies xbrl
Platform: UNKNOWN
Classifier: Programming Language :: Python :: 3
Classifier: License :: OSI Approved :: MIT License
Classifier: Operating System :: OS Independent
Requires-Python: >=3.6
Requires-Dist: solaris-api (>=1.0.0)
Requires-Dist: pandas
Requires-Dist: pytrends
Requires-Dist: yfinance
